svm-kernels/__init__.py
svm-kernels/k_functions.py
svm-kernels/kernels.py
svm-kernels/polynomials.py
svm_kernels/__init__.py
svm_kernels/k_functions.py
svm_kernels/kernels.py
svm_kernels/polynomials.py
svm_kernels-0.0.3.dist-info/LICENSE
svm_kernels-0.0.3.dist-info/METADATA
svm_kernels-0.0.3.dist-info/WHEEL
svm_kernels-0.0.3.dist-info/top_level.txt
svm_kernels-0.0.3.dist-info/RECORD
