Metadata-Version: 2.1
Name: svm-kernels
Version: 0.0.3
Summary: Orthogonal Polynomial Kernels for SVM
Home-page: https://github.com/benayas1/svm-kernels
Author: Alberto Benayas
Author-email: benayas1@gmail.com
License: UNKNOWN
Platform: UNKNOWN
Classifier: Programming Language :: Python :: 3
Classifier: License :: OSI Approved :: MIT License
Classifier: Operating System :: OS Independent
Requires-Python: >=3.6
